django_mama_cas-2.4.0.dist-info/METADATA
django_mama_cas-2.4.0.dist-info/RECORD
django_mama_cas-2.4.0.dist-info/WHEEL
django_mama_cas-2.4.0.dist-info/top_level.txt
mama_cas/__init__.py
mama_cas/callbacks.py
mama_cas/cas.py
mama_cas/compat.py
mama_cas/exceptions.py
mama_cas/forms.py
mama_cas/mixins.py
mama_cas/models.py
mama_cas/request.py
mama_cas/response.py
mama_cas/urls.py
mama_cas/utils.py
mama_cas/views.py
mama_cas/locale/zh_CN/LC_MESSAGES/django.mo
mama_cas/locale/zh_CN/LC_MESSAGES/django.po
mama_cas/management/__init__.py
mama_cas/management/commands/__init__.py
mama_cas/management/commands/checkservice.py
mama_cas/management/commands/cleanupcas.py
mama_cas/migrations/0001_initial.py
mama_cas/migrations/__init__.py
mama_cas/services/__init__.py
mama_cas/services/backends.py
mama_cas/templates/mama_cas/__base.html
mama_cas/templates/mama_cas/__login.html
mama_cas/templates/mama_cas/__warn.html
mama_cas/templates/mama_cas/_messages.html
mama_cas/templates/mama_cas/login.html
mama_cas/templates/mama_cas/warn.html
mama_cas/tests/__init__.py
mama_cas/tests/backends.py
mama_cas/tests/callbacks.py
mama_cas/tests/factories.py
mama_cas/tests/settings.py
mama_cas/tests/test_callbacks.py
mama_cas/tests/test_commands.py
mama_cas/tests/test_forms.py
mama_cas/tests/test_models.py
mama_cas/tests/test_request.py
mama_cas/tests/test_response.py
mama_cas/tests/test_services.py
mama_cas/tests/test_utils.py
mama_cas/tests/test_views.py
mama_cas/tests/utils.py
