Metadata-Version: 2.1
Name: django-mama-cas
Version: 2.4.0
Summary: A Django Central Authentication Service (CAS) single sign-on server
Home-page: https://github.com/jbittel/django-mama-cas
Author: Jason Bittel
Author-email: jason.bittel@gmail.com
License: BSD
Download-URL: https://pypi.python.org/pypi/django-mama-cas/
Keywords: auth,authentication,cas,django,single sign-on,sso
Platform: UNKNOWN
Classifier: Development Status :: 5 - Production/Stable
Classifier: Environment :: Web Environment
Classifier: Framework :: Django
Classifier: Intended Audience :: Developers
Classifier: License :: OSI Approved :: BSD License
Classifier: Operating System :: OS Independent
Classifier: Programming Language :: Python
Classifier: Programming Language :: Python :: 2
Classifier: Programming Language :: Python :: 2.7
Classifier: Programming Language :: Python :: 3
Classifier: Programming Language :: Python :: 3.3
Classifier: Programming Language :: Python :: 3.4
Classifier: Programming Language :: Python :: 3.5
Classifier: Topic :: Software Development :: Libraries :: Python Modules
Classifier: Topic :: System :: Systems Administration :: Authentication/Directory
Requires-Dist: requests (<3.0.0,>=2.0.0)
